notion_to_markdown/__init__.py
notion_to_markdown/base.py
notion_to_markdown/main.py
notion_to_markdown/types/__init__.py
notion_to_markdown/types/notion_types.py
notion_to_markdown/utils/__init__.py
notion_to_markdown/utils/md.py
notion_to_markdown/utils/notion.py
tests/__init__.py
tests/test_base.py
tests/test_md.py
notion_to_markdown-0.1.5.dist-info/LICENSE
notion_to_markdown-0.1.5.dist-info/METADATA
notion_to_markdown-0.1.5.dist-info/WHEEL
notion_to_markdown-0.1.5.dist-info/top_level.txt
notion_to_markdown-0.1.5.dist-info/RECORD
