Metadata-Version: 2.2
Name: notion-to-markdown
Version: 0.1.5
Summary: A package to convert Notion content into Markdown format
Home-page: https://github.com/atb00ker/notion-to-markdown
Author: Ajay Tripathi
Author-email: ajay39in@gmail.com
Project-URL: Bug Tracker, https://github.com/atb00ker/notion-to-markdown/issues
Project-URL: Source Code, https://github.com/atb00ker/notion-to-markdown
Keywords: Convert,Notion,Markdown
Classifier: Programming Language :: Python :: 3.7
Classifier: License :: OSI Approved :: MIT License
Classifier: Operating System :: OS Independent
Requires-Python: >=3.7
License-File: LICENSE
Requires-Dist: httpx
Requires-Dist: pytablewriter
Requires-Dist: notion-client
Provides-Extra: async
Requires-Dist: asyncio; extra == "async"
Dynamic: author
Dynamic: author-email
Dynamic: classifier
Dynamic: description
Dynamic: description-content-type
Dynamic: home-page
Dynamic: keywords
Dynamic: project-url
Dynamic: provides-extra
Dynamic: requires-dist
Dynamic: requires-python
Dynamic: summary
